accesslog/__init__.py
accesslog/__main__.py
accesslog/clparser.py
accesslog-0.1.0b5.dist-info/LICENSE
accesslog-0.1.0b5.dist-info/METADATA
accesslog-0.1.0b5.dist-info/WHEEL
accesslog-0.1.0b5.dist-info/entry_points.txt
accesslog-0.1.0b5.dist-info/top_level.txt
accesslog-0.1.0b5.dist-info/RECORD
