Metadata-Version: 2.1
Name: accesslog
Version: 0.1.0b5
Summary: Web server access log parser and CLI tool with added features for web archive replay logs
Home-page: https://github.com/oduwsdl/archive-accesslog
Author: Sawood Alam
Author-email: ibnesayeed@gmail.com
License: MIT License
Platform: UNKNOWN
Classifier: Programming Language :: Python :: 3.6
Classifier: Programming Language :: Python :: 3.7
Classifier: License :: OSI Approved :: MIT License
Classifier: Operating System :: OS Independent
Classifier: Topic :: Internet :: Log Analysis
Provides: accesslog
Requires-Python: >=3.6
